nebulog/__init__.py
nebulog/config.py
nebulog/core.py
nebulog/examples/__init__.py
nebulog/examples/constants.py
nebulog/examples/highlighters.py
nebulog/examples/renderers.py
nebulog/handler.py
nebulog/interfaces.py
nebulog/renderers/__init__.py
nebulog/renderers/message.py
nebulog/renderers/time.py
nebulog/types.py
nebulog-0.1.0.dist-info/METADATA
nebulog-0.1.0.dist-info/WHEEL
nebulog-0.1.0.dist-info/licenses/LICENCE
nebulog-0.1.0.dist-info/RECORD
