Metadata-Version: 2.4
Name: nebulog
Version: 0.1.0
Summary: Rich output spectacularly merged into Loguru to serve as the cradle of your stellar logs
License: MIT
License-File: LICENCE
Author: Manoel Pereira de Queiroz
Author-email: mpq.dev@pm.me
Maintainer: Manoel Pereira de Queiroz
Maintainer-email: mpq.dev@pm.me
Requires-Python: >=3.10
Classifier: Development Status :: 1 - Planning
Classifier: Intended Audience :: Developers
Classifier: License :: OSI Approved :: MIT License
Classifier: Operating System :: OS Independent
Classifier: Programming Language :: Python :: 3
Classifier: Programming Language :: Python :: 3.10
Classifier: Programming Language :: Python :: 3.11
Classifier: Programming Language :: Python :: 3.12
Classifier: Programming Language :: Python :: 3.13
Classifier: Programming Language :: Python :: 3.14
Classifier: Topic :: Software Development :: Libraries :: Python Modules
Requires-Dist: loguru (>=0.7.3,<0.8.0)
Requires-Dist: rich (>=14.1.0,<15.0.0)
Requires-Dist: typing-extensions (>=4.15.0,<5.0.0)
Project-URL: Contributing Guidelines, https://gitlab.com/galactipy/nebulog/-/tree/master/CONTRIBUTING.md
Project-URL: Homepage, https://gitlab.com/galactipy/nebulog
Project-URL: Repository, https://gitlab.com/galactipy/nebulog
Project-URL: Work Item Tracker, https://gitlab.com/galactipy/nebulog/-/issues
